{
  "patterns": {
    "aws": {
      "access_key": {
        "regex": "(AKIA|ASIA)[0-9A-Z]{16}",
        "description": "AWS Access Key ID",
        "severity": "critical",
        "examples": ["AKIAIOSFODNN7EXAMPLE", "ASIATESTACCESSKEY123"]
      },
      "secret_key": {
        "regex": "aws_secret_access_key[\"'\\s:=]+[A-Za-z0-9/+=]{40}",
        "description": "AWS Secret Access Key",
        "severity": "critical",
        "examples": ["aws_secret_access_key = wJalrXUtnFEMI/K7MDENG/bPxRfiCYEXAMPLEKEY"]
      },
      "session_token": {
        "regex": "AWS[\"']?\\s*:\\s*[\"']?[A-Za-z0-9/+=]{100,}",
        "description": "AWS Session Token",
        "severity": "critical"
      }
    },
    "github": {
      "personal_access_token": {
        "regex": "ghp_[0-9a-zA-Z]{36}",
        "description": "GitHub Personal Access Token",
        "severity": "critical",
        "examples": ["ghp_1234567890abcdefghijklmnopqrstuvwx"]
      },
      "fine_grained_pat": {
        "regex": "github_pat_[0-9a-zA-Z]{22}_[0-9a-zA-Z]{59}",
        "description": "GitHub Fine-grained Personal Access Token",
        "severity": "critical"
      },
      "oauth_token": {
        "regex": "gho_[0-9a-zA-Z]{36}",
        "description": "GitHub OAuth Access Token",
        "severity": "critical"
      },
      "app_token": {
        "regex": "ghu_[0-9a-zA-Z]{36}",
        "description": "GitHub App User Access Token",
        "severity": "critical"
      },
      "server_token": {
        "regex": "ghs_[0-9a-zA-Z]{36}",
        "description": "GitHub App Server-to-Server Token",
        "severity": "critical"
      },
      "refresh_token": {
        "regex": "ghr_[0-9a-zA-Z]{36}",
        "description": "GitHub Refresh Token",
        "severity": "critical"
      }
    },
    "google": {
      "api_key": {
        "regex": "AIza[0-9A-Za-z_\\-]{35}",
        "description": "Google API Key",
        "severity": "high",
        "examples": ["AIzaSyDaGmWKa4JsXZ-HjGw7ISLn_3namBGewQe"]
      },
      "oauth_client": {
        "regex": "[0-9]+-[0-9A-Za-z_]{32}\\.apps\\.googleusercontent\\.com",
        "description": "Google OAuth Client ID",
        "severity": "medium"
      },
      "service_account": {
        "regex": "\"type\"\\s*:\\s*\"service_account\"",
        "description": "Google Service Account JSON",
        "severity": "critical"
      }
    },
    "slack": {
      "token": {
        "regex": "xox[pbar]-[0-9]{10,13}-[0-9]{10,13}-[0-9]{10,13}-[a-z0-9]{32}",
        "description": "Slack Token",
        "severity": "high",
        "examples": ["xoxb-123456789012-123456789012-abcdefghijklmnopqrstuvwx"]
      },
      "webhook": {
        "regex": "https://hooks\\.slack\\.com/services/T[a-zA-Z0-9_]{8}/B[a-zA-Z0-9_]{8}/[a-zA-Z0-9_]{24}",
        "description": "Slack Webhook URL",
        "severity": "high"
      }
    },
    "stripe": {
      "secret_key": {
        "regex": "sk_live_[0-9a-zA-Z]{24,}",
        "description": "Stripe Live Secret Key",
        "severity": "critical",
        "examples": ["sk_live_1234567890abcdefghijklmn"]
      },
      "restricted_key": {
        "regex": "rk_live_[0-9a-zA-Z]{24,}",
        "description": "Stripe Live Restricted Key",
        "severity": "high"
      },
      "test_key": {
        "regex": "sk_test_[0-9a-zA-Z]{24,}",
        "description": "Stripe Test Secret Key",
        "severity": "medium"
      }
    },
    "private_keys": {
      "rsa": {
        "regex": "-----BEGIN RSA PRIVATE KEY-----",
        "description": "RSA Private Key",
        "severity": "critical"
      },
      "openssh": {
        "regex": "-----BEGIN OPENSSH PRIVATE KEY-----",
        "description": "OpenSSH Private Key",
        "severity": "critical"
      },
      "dsa": {
        "regex": "-----BEGIN DSA PRIVATE KEY-----",
        "description": "DSA Private Key",
        "severity": "critical"
      },
      "ec": {
        "regex": "-----BEGIN EC PRIVATE KEY-----",
        "description": "EC Private Key",
        "severity": "critical"
      },
      "pgp": {
        "regex": "-----BEGIN PGP PRIVATE KEY BLOCK-----",
        "description": "PGP Private Key",
        "severity": "critical"
      },
      "pkcs8": {
        "regex": "-----BEGIN PRIVATE KEY-----",
        "description": "PKCS#8 Private Key",
        "severity": "critical"
      }
    },
    "database": {
      "postgres": {
        "regex": "postgres://[a-zA-Z0-9_]+:[a-zA-Z0-9_!@#$%^&*]+@[a-zA-Z0-9\\.\\-]+:[0-9]+/[a-zA-Z0-9_]+",
        "description": "PostgreSQL Connection String",
        "severity": "high",
        "examples": ["postgres://user:password@localhost:5432/dbname"]
      },
      "mysql": {
        "regex": "mysql://[a-zA-Z0-9_]+:[a-zA-Z0-9_!@#$%^&*]+@[a-zA-Z0-9\\.\\-]+:[0-9]+/[a-zA-Z0-9_]+",
        "description": "MySQL Connection String",
        "severity": "high"
      },
      "mongodb": {
        "regex": "mongodb(\\+srv)?://[a-zA-Z0-9_]+:[a-zA-Z0-9_!@#$%^&*]+@[a-zA-Z0-9\\.\\-]+/[a-zA-Z0-9_]+",
        "description": "MongoDB Connection String",
        "severity": "high"
      },
      "redis": {
        "regex": "redis://[a-zA-Z0-9_]+:[a-zA-Z0-9_!@#$%^&*]+@[a-zA-Z0-9\\.\\-]+:[0-9]+",
        "description": "Redis Connection String",
        "severity": "high"
      }
    },
    "jwt": {
      "token": {
        "regex": "eyJ[A-Za-z0-9_\\-]+\\.eyJ[A-Za-z0-9_\\-]+\\.[A-Za-z0-9_\\-]+",
        "description": "JSON Web Token (JWT)",
        "severity": "medium"
      }
    },
    "oauth": {
      "secret": {
        "regex": "oauth[_\\-]?secret[\"'\\s:=]+[A-Za-z0-9_\\-]{20,}",
        "description": "OAuth Secret",
        "severity": "high"
      },
      "client_secret": {
        "regex": "client[_\\-]?secret[\"'\\s:=]+[A-Za-z0-9_\\-]{20,}",
        "description": "OAuth Client Secret",
        "severity": "high"
      }
    },
    "generic": {
      "api_key": {
        "regex": "api[_\\-]?key[\"'\\s:=]+['\"][A-Za-z0-9_\\-]{20,}['\"]",
        "description": "Generic API Key",
        "severity": "medium"
      },
      "password": {
        "regex": "password[\"'\\s:=]+['\"][^'\"]{8,}['\"]",
        "description": "Hardcoded Password",
        "severity": "high"
      },
      "token": {
        "regex": "token[\"'\\s:=]+['\"][A-Za-z0-9_\\-]{20,}['\"]",
        "description": "Generic Token",
        "severity": "medium"
      },
      "secret": {
        "regex": "secret[\"'\\s:=]+['\"][A-Za-z0-9_\\-]{20,}['\"]",
        "description": "Generic Secret",
        "severity": "medium"
      }
    },
    "azure": {
      "storage_account": {
        "regex": "DefaultEndpointsProtocol=https;AccountName=[a-z0-9]+;AccountKey=[A-Za-z0-9+/=]{88};",
        "description": "Azure Storage Account Connection String",
        "severity": "critical"
      },
      "service_principal": {
        "regex": "\"appId\"\\s*:\\s*\"[a-f0-9-]{36}\"",
        "description": "Azure Service Principal",
        "severity": "high"
      }
    },
    "twilio": {
      "api_key": {
        "regex": "SK[a-z0-9]{32}",
        "description": "Twilio API Key",
        "severity": "high"
      },
      "account_sid": {
        "regex": "AC[a-z0-9]{32}",
        "description": "Twilio Account SID",
        "severity": "medium"
      }
    },
    "sendgrid": {
      "api_key": {
        "regex": "SG\\.[a-zA-Z0-9_\\-]{22}\\.[a-zA-Z0-9_\\-]{43}",
        "description": "SendGrid API Key",
        "severity": "high"
      }
    },
    "mailgun": {
      "api_key": {
        "regex": "key-[0-9a-zA-Z]{32}",
        "description": "Mailgun API Key",
        "severity": "high"
      }
    },
    "npm": {
      "token": {
        "regex": "npm_[A-Za-z0-9]{36}",
        "description": "NPM Access Token",
        "severity": "high"
      }
    },
    "pypi": {
      "token": {
        "regex": "pypi-AgEIcHlwaS5vcmc[A-Za-z0-9\\-_]{50,}",
        "description": "PyPI Upload Token",
        "severity": "high"
      }
    },
    "docker": {
      "auth": {
        "regex": "\"auth\"\\s*:\\s*\"[A-Za-z0-9+/=]{40,}\"",
        "description": "Docker Registry Auth",
        "severity": "high"
      }
    },
    "heroku": {
      "api_key": {
        "regex": "heroku[_\\-]?api[_\\-]?key[\"'\\s:=]+[A-Za-z0-9\\-]{36}",
        "description": "Heroku API Key",
        "severity": "high"
      }
    },
    "firebase": {
      "api_key": {
        "regex": "AIza[0-9A-Za-z\\-_]{35}",
        "description": "Firebase API Key",
        "severity": "high"
      }
    },
    "cloudflare": {
      "api_key": {
        "regex": "cloudflare[_\\-]?api[_\\-]?key[\"'\\s:=]+[A-Za-z0-9\\-]{37}",
        "description": "Cloudflare API Key",
        "severity": "high"
      }
    }
  },
  "metadata": {
    "version": "1.0",
    "last_updated": "2025-10-29",
    "pattern_count": 50,
    "categories": [
      "aws", "github", "google", "slack", "stripe",
      "private_keys", "database", "jwt", "oauth",
      "azure", "twilio", "sendgrid", "mailgun",
      "npm", "pypi", "docker", "heroku", "firebase", "cloudflare"
    ]
  }
}
